<?xml version="1.0" encoding="windows-1252" ?>
<!DOCTYPE ViewObject SYSTEM "jbo_03_01.dtd">
<!---->
<ViewObject
  xmlns="http://xmlns.oracle.com/bc4j"
  Name="EmpDetails"
  Version="11.1.2.59.47"
  SelectList="Employees.EMPLOYEE_ID, 
       Employees.FIRST_NAME, 
       Employees.LAST_NAME, 
       Employees.EMAIL, 
       Employees.SALARY, 
       Employees.HIRE_DATE, 
       Employees.JOB_ID, 
       Departments.DEPARTMENT_ID, 
       Departments.DEPARTMENT_NAME"
  FromList="EMPLOYEES Employees, DEPARTMENTS Departments"
  Where="Employees.DEPARTMENT_ID = Departments.DEPARTMENT_ID"
  BindingStyle="OracleName"
  CustomQuery="false"
  PageIterMode="Full"
  UseGlueCode="false">
  <Properties>
    <SchemaBasedProperties>
      <LABEL
        ResId="demo.model.EmpDetails_LABEL"/>
    </SchemaBasedProperties>
  </Properties>
  <ViewAccessor
    Name="JobsView1"
    ViewObjectName="demo.model.JobsView"
    RowLevelBinds="true"/>
  <ListBinding
    Name="LOV_JobId"
    ListVOName="JobsView1"
    ListRangeSize="-1"
    ComboRowCountHint="10"
    NullValueFlag="none"
    MRUCount="0">
    <AttrArray Name="AttrNames">
      <Item Value="JobId"/>
    </AttrArray>
    <AttrArray Name="ListAttrNames">
      <Item Value="JobId"/>
    </AttrArray>
    <AttrArray Name="ListDisplayAttrNames">
      <Item Value="JobTitle"/>
    </AttrArray>
    <DisplayCriteria/>
  </ListBinding>
  <EntityUsage
    Name="Employees"
    Entity="demo.model.Employees"/>
  <EntityUsage
    Name="Departments"
    Entity="demo.model.Departments"
    Association="demo.model.EmpDeptFkAssoc"
    AssociationEnd="demo.model.EmpDeptFkAssoc.Departments1"
    SourceUsage="demo.model.EmpDetails.Employees"
    ReadOnly="true"
    Reference="true"
    DeleteParticipant="false"
    JoinType="INNER JOIN">
    <DesignTime>
      <AttrArray Name="_srcAttributes">
        <Item Value="demo.model.Employees.DepartmentId"/>
      </AttrArray>
      <AttrArray Name="_dstAttributes">
        <Item Value="demo.model.Departments.DepartmentId"/>
      </AttrArray>
    </DesignTime>
  </EntityUsage>
  <ViewAttribute
    Name="EmployeeId"
    IsNotNull="true"
    PrecisionRule="true"
    EntityAttrName="EmployeeId"
    EntityUsage="Employees"
    AliasName="EMPLOYEE_ID"/>
  <ViewAttribute
    Name="FirstName"
    PrecisionRule="true"
    EntityAttrName="FirstName"
    EntityUsage="Employees"
    AliasName="FIRST_NAME"/>
  <ViewAttribute
    Name="LastName"
    IsNotNull="true"
    PrecisionRule="true"
    EntityAttrName="LastName"
    EntityUsage="Employees"
    AliasName="LAST_NAME"/>
  <ViewAttribute
    Name="Email"
    IsUnique="true"
    IsNotNull="true"
    PrecisionRule="true"
    EntityAttrName="Email"
    EntityUsage="Employees"
    AliasName="EMAIL"/>
  <ViewAttribute
    Name="Salary"
    PrecisionRule="true"
    EntityAttrName="Salary"
    EntityUsage="Employees"
    AliasName="SALARY"/>
  <ViewAttribute
    Name="HireDate"
    IsNotNull="true"
    PrecisionRule="true"
    EntityAttrName="HireDate"
    EntityUsage="Employees"
    AliasName="HIRE_DATE"/>
  <ViewAttribute
    Name="JobId"
    IsNotNull="true"
    PrecisionRule="true"
    EntityAttrName="JobId"
    EntityUsage="Employees"
    AliasName="JOB_ID"
    LOVName="LOV_JobId">
    <Properties>
      <SchemaBasedProperties>
        <CONTROLTYPE
          Value="combo_lov"/>
      </SchemaBasedProperties>
    </Properties>
  </ViewAttribute>
  <ViewAttribute
    Name="DepartmentId"
    IsNotNull="true"
    PrecisionRule="true"
    EntityAttrName="DepartmentId"
    EntityUsage="Departments"
    AliasName="DEPARTMENT_ID"/>
  <ViewAttribute
    Name="DepartmentName"
    IsNotNull="true"
    PrecisionRule="true"
    EntityAttrName="DepartmentName"
    EntityUsage="Departments"
    AliasName="DEPARTMENT_NAME"/>
  <ViewAttribute
    Name="AnnualSalary"
    IsUpdateable="false"
    IsSelected="false"
    IsPersistent="false"
    PrecisionRule="true"
    Type="oracle.jbo.domain.Number"
    ColumnType="NUMBER"
    AliasName="VIEW_ATTR"
    SQLType="NUMERIC">
    <RecalcCondition><![CDATA[true]]></RecalcCondition>
    <TransientExpression><![CDATA[Salary * 12]]></TransientExpression>
  </ViewAttribute>
  <AttrArray Name="KeyAttributes">
    <Item Value="EmployeeId"/>
  </AttrArray>
  <ResourceBundle>
    <PropertiesBundle
      PropertiesFile="demo.model.ModelBundle"/>
  </ResourceBundle>
</ViewObject>
